soundstorm_superfeel/__init__.py
soundstorm_superfeel/attend.py
soundstorm_superfeel/soundstorm.py
soundstorm_superfeel/trainer.py
soundstorm_superfeel-0.4.5.dist-info/LICENSE
soundstorm_superfeel-0.4.5.dist-info/METADATA
soundstorm_superfeel-0.4.5.dist-info/WHEEL
soundstorm_superfeel-0.4.5.dist-info/top_level.txt
soundstorm_superfeel-0.4.5.dist-info/RECORD
