Metadata-Version: 2.1
Name: soundstorm-superfeel
Version: 0.4.5
Summary: SoundStorm - Efficient Parallel Audio Generation from Google Deepmind, in Pytorch
Home-page: https://github.com/osehmathias/soundstorm-superfeel
Author: Phil Wang & Oseh Mathias
Author-email: o@matmail.me
License: MIT
Keywords: artificial intelligence,deep learning,transformers,attention mechanism,audio generation
Classifier: Development Status :: 4 - Beta
Classifier: Intended Audience :: Developers
Classifier: Topic :: Scientific/Engineering :: Artificial Intelligence
Classifier: License :: OSI Approved :: MIT License
Classifier: Programming Language :: Python :: 3.6
License-File: LICENSE
Requires-Dist: accelerate
Requires-Dist: audiolm-superfeel >=1.2.8
Requires-Dist: beartype
Requires-Dist: classifier-free-guidance-pytorch >=0.1.5
Requires-Dist: gateloop-transformer >=0.1.1
Requires-Dist: einops >=0.6.1
Requires-Dist: spear-tts-pytorch >=0.4.0
Requires-Dist: torch >=1.6
